{"is_source_file": true, "format": "TypeScript (TSX)", "description": "This file defines the index route for a Remix app. It sets page metadata and redirects to the '/notes' route.", "external_files": ["@remix-run/node"], "external_methods": ["redirect"], "published": ["meta", "loader", "default"], "classes": [], "methods": [{"name": "meta", "description": "Provides metadata for the page, such as title and description."}, {"name": "loader", "description": "Asynchronous function that redirects to the '/notes' route."}, {"name": "Index", "description": "React component for the index route that renders nothing."}], "calls": ["redirect"], "search-terms": ["remix", "loader", "redirect", "index route", "meta function", "tsx"], "state": 2, "file_id": 4, "knowledge_revision": 51, "git_revision": "5a859fb4e88280eb088f51ec29797756ddc0d4c6", "revision_history": [{"24": "5a859fb4e88280eb088f51ec29797756ddc0d4c6"}, {"31": "5a859fb4e88280eb088f51ec29797756ddc0d4c6"}, {"47": "5a859fb4e88280eb088f51ec29797756ddc0d4c6"}, {"51": "5a859fb4e88280eb088f51ec29797756ddc0d4c6"}], "ctags": [], "hash": "196f24617b4edfb1df2d16f977c8419f", "format-version": 4, "code-base-name": "notes_frontend", "filename": "notes_frontend/app/routes/_index.tsx"}